{"tagline":"Personal notes for anything related to studying, mainly for actuarial exams.","note":"Don't delete this file! It's used internally to help with page regeneration.","body":"# Study notes\r\n\r\nPersonal notes for anything related to studying, mainly for actuarial exams.\r\n\r\n\r\n## ST7\r\n\r\n### Items needed from Glossary\r\nPages from overall eBook version of notes:\r\n* 01: 33 - 34\r\n* 02: 76\r\n* 03: 143\r\n* 04: 184\r\n* 05: 239\r\n* 06: 274\r\n* 07: 325\r\n* 08: 350\r\n* 09: 388\r\n* 10: 445\r\n* 11: 472\r\n* 12: 494\r\n* 13: 570\r\n* 14: -\r\n* 15: 653\r\n* 16: 684\r\n* 17: 729\r\n* 18: -\r\n* 19: -\r\n* 20: -\r\n* 21: -\r\n* 22: 895\r\n* 23: 923\r\n* 24: 958\r\n* 25: 984\r\n* 26: 1027\r\n\r\n* All: 33 - 34, 76, 143, 184, 239, 274, 325, 350, 388, 445, 472, 494, 570, 653, 684, 729, 895, 923, 958, 984, 1027\r\n\r\n### Glossary\r\nThe glossary is on pages 1037 - 1087.\r\n","name":"Study notes","google":""}